plump/__init__.py
plump/__version__.py
plump/core.py
plump/crypto.py
plump/easytime.py
plump/useragent.py
plump-0.0.2.dist-info/LICENSE
plump-0.0.2.dist-info/METADATA
plump-0.0.2.dist-info/WHEEL
plump-0.0.2.dist-info/top_level.txt
plump-0.0.2.dist-info/RECORD
