Metadata-Version: 2.1
Name: plump
Version: 0.0.2
Summary: Python常用函数的封装
Home-page: https://github.com/founddev/plump
Author: Cheng Shuang
Author-email: niie@163.com
License: MIT
Platform: UNKNOWN
Classifier: License :: OSI Approved :: MIT License
Classifier: Programming Language :: Python
Classifier: Programming Language :: Python :: 3
Classifier: Programming Language :: Python :: 3.6
Classifier: Programming Language :: Python :: Implementation :: CPython
Classifier: Programming Language :: Python :: Implementation :: PyPy
Requires-Python: >=3.4.0
Requires-Dist: rsa
Requires-Dist: pyDes
Requires-Dist: arrow
